varpickler/README.md
varpickler/__init__.py
varpickler/requirements.txt
varpickler/thirdparty.json
varpickler-0.10.dist-info/LICENSE.rst
varpickler-0.10.dist-info/METADATA
varpickler-0.10.dist-info/WHEEL
varpickler-0.10.dist-info/top_level.txt
varpickler-0.10.dist-info/RECORD
