Metadata-Version: 2.1
Name: varpickler
Version: 0.10
Summary: pickle / unpickle variables
Home-page: https://github.com/hansalemaos/varpickler
Author: Johannes Fischer
Author-email: aulasparticularesdealemaosp@gmail.com
License: MIT
Keywords: pickle,unpickle
Classifier: Development Status :: 4 - Beta
Classifier: Programming Language :: Python :: 3 :: Only
Classifier: Programming Language :: Python :: 3.10
Classifier: Topic :: Software Development :: Libraries :: Python Modules
Classifier: Topic :: Utilities
License-File: LICENSE.rst
Requires-Dist: dill
